simple_json_log_formatter/__init__.py
simple_json_log_formatter/formatter.py
simple_json_log_formatter-0.5.5.dist-info/METADATA
simple_json_log_formatter-0.5.5.dist-info/WHEEL
simple_json_log_formatter-0.5.5.dist-info/top_level.txt
simple_json_log_formatter-0.5.5.dist-info/RECORD
