Metadata-Version: 2.1
Name: simple-json-log-formatter
Version: 0.5.5
Summary: Simple log formatter for Logstash-compatible JSON output
Home-page: https://github.com/flaviocpontes/simple_json_log_formatter
Author: Flávio Cardoso Ferreira Pontes
Author-email: flaviocpontes@gmail.com
License: MIT
Download-URL: https://github.com/flaviocpontes/simple_json_log_formatter/archive/0.5.5.tar.gz
Keywords: logging json log output formatter
Platform: UNKNOWN
Classifier: Development Status :: 5 - Production/Stable
Classifier: Intended Audience :: Developers
Classifier: License :: OSI Approved :: MIT License
Classifier: Programming Language :: Python :: 2.7
Classifier: Programming Language :: Python :: 3.4
Classifier: Programming Language :: Python :: 3.5
Classifier: Programming Language :: Python :: 3.6
Requires-Python: >=2.7
Requires-Dist: six
Provides-Extra: dev
Requires-Dist: freezegun ; extra == 'dev'
Requires-Dist: coverage ; extra == 'dev'
Requires-Dist: codecov ; extra == 'dev'
